medusa/__init__.py
medusa/core/Medusa.py
medusa/core/MedusaGraph.py
medusa/core/__init__.py
medusa/core/driver_loader.py
medusa/core/vessel.py
medusa/defaults/GraphDefaults.json
medusa/defaults/__init__.py
medusa/defaults/demo_exp_mini.json
medusa/frontend/MedusaDesigner.py
medusa/frontend/__init__.py
medusa/frontend/api.py
medusa/frontend/depracated/launch.py
medusa/frontend/static/default_design.json
medusa/frontend/static/index.html
medusa/frontend/static/script.js
medusa/frontend/static/style.css
medusa/frontend/static/icons/balance.svg
medusa/frontend/static/icons/hotplate.svg
medusa/frontend/static/icons/pump.svg
medusa/frontend/static/icons/relay.svg
medusa/frontend/static/icons/serialdevice.svg
medusa/frontend/static/icons/shaker.svg
medusa/frontend/static/icons/valve.svg
medusa/frontend/static/icons/vessel.svg
medusa/utils/FileHandling.py
medusa/utils/MedusaErrors.py
medusa/utils/__init__.py
medusa_sdl-0.1.5.dist-info/licenses/LICENSE
themachine_pycontrol/__init__.py
themachine_pycontrol/Utils/FileHandling.py
themachine_pycontrol/Utils/MedusaErrors.py
themachine_pycontrol/Utils/__init__.py
themachine_pycontrol/core/Medusa.py
themachine_pycontrol/core/MedusaGraph.py
themachine_pycontrol/core/Vessel.py
themachine_pycontrol/core/__init__.py
themachine_pycontrol/defaults/__init__.py
themachine_pycontrol/frontend/MedusaDesigner.py
themachine_pycontrol/frontend/__init__.py
themachine_pycontrol/frontend/depracated/launch.py
medusa_sdl-0.1.5.dist-info/METADATA
medusa_sdl-0.1.5.dist-info/WHEEL
medusa_sdl-0.1.5.dist-info/entry_points.txt
medusa_sdl-0.1.5.dist-info/top_level.txt
medusa_sdl-0.1.5.dist-info/RECORD
