Metadata-Version: 2.4
Name: medusa-sdl
Version: 0.1.5
Summary: MEDUSA: Modular, Expandable Discovery and Understanding Synthesis Apparatus
Author-email: Han Hao <hann.hao@utoronto.ca>, Felix Strieth-Kalthoff <f.striethkalthoff@utoronto.com>
License-Expression: MIT
Project-URL: Homepage, https://gitlab.com/aspuru-guzik-group/self-driving-lab/instruments/themachine-pycontrol
Keywords: chemistry,synthesis,laboratory,automation,medusa,scientific,engineering
Classifier: Programming Language :: Python :: 3
Classifier: Operating System :: OS Independent
Classifier: Intended Audience :: Science/Research
Classifier: Topic :: Scientific/Engineering
Classifier: Topic :: Scientific/Engineering :: Chemistry
Classifier: Topic :: Software Development :: Libraries :: Python Modules
Requires-Python: >=3.10
License-File: LICENSE
Requires-Dist: networkx
Requires-Dist: matplotlib
Requires-Dist: flask
Requires-Dist: pyserial
Requires-Dist: matterlab_serial_device
Provides-Extra: pumps
Requires-Dist: matterlab_pumps; extra == "pumps"
Provides-Extra: valves
Requires-Dist: matterlab_valves; extra == "valves"
Provides-Extra: hotplates
Requires-Dist: matterlab_hotplates; extra == "hotplates"
Provides-Extra: relays
Requires-Dist: matterlab_relays; extra == "relays"
Provides-Extra: shakers
Requires-Dist: matterlab_shakers; extra == "shakers"
Provides-Extra: balances
Requires-Dist: matterlab_balances; extra == "balances"
Provides-Extra: all
Requires-Dist: matterlab_pumps; extra == "all"
Requires-Dist: matterlab_valves; extra == "all"
Requires-Dist: matterlab_hotplates; extra == "all"
Requires-Dist: matterlab_relays; extra == "all"
Requires-Dist: matterlab_shakers; extra == "all"
Requires-Dist: matterlab_balances; extra == "all"
Dynamic: license-file
